lazyr/__init__.py
lazyr/__version__.py
lazyr/core.py
lazyr-0.0.24.dist-info/licenses/LICENSE
lazyr-0.0.24.dist-info/METADATA
lazyr-0.0.24.dist-info/WHEEL
lazyr-0.0.24.dist-info/top_level.txt
lazyr-0.0.24.dist-info/RECORD
